apscale_installer/__init__.py
apscale_installer/__main__.py
apscale_installer-0.4.dist-info/LICENSE
apscale_installer-0.4.dist-info/METADATA
apscale_installer-0.4.dist-info/WHEEL
apscale_installer-0.4.dist-info/entry_points.txt
apscale_installer-0.4.dist-info/top_level.txt
apscale_installer-0.4.dist-info/RECORD
