Metadata-Version: 2.1
Name: apscale_installer
Version: 0.4
Summary: Advanced Pipeline for Simple yet Comprehensive AnaLysEs of DNA metabarcoding data - Conda installer (workaround)
Home-page: https://pypi.org/project/apscale_installer/
Author: Till-Hendrik Macher
Author-email: macher@uni-trier.de
License: MIT
Classifier: Programming Language :: Python :: 3
Classifier: License :: OSI Approved :: MIT License
Classifier: Operating System :: OS Independent
Requires-Python: >=3.10
License-File: LICENSE
Requires-Dist: Requests ==2.32.3
